branch_assigner/branch_assigner.py
external/shared/fixtures/env_helper.py
external/shared/fixtures/sys_path_helper.py
message_mgr/message.py
plugin/plugin_manager.py
boa_fm-0.0.13.dist-info/METADATA
boa_fm-0.0.13.dist-info/WHEEL
boa_fm-0.0.13.dist-info/top_level.txt
boa_fm-0.0.13.dist-info/RECORD
