Metadata-Version: 2.1
Name: boa-fm
Version: 0.0.13
Summary: framework for making monads. this provides the tools to write the core logic for the application
Author-email: Dinesh Kamath <dmkamath@gmail.com>
Project-URL: Homepage, https://github.com/dmkamath/quick_bytes
Project-URL: Bug Tracker, https://github.com/dmkamath/quick_bytes/issues
Classifier: Programming Language :: Python :: 3
Classifier: License :: OSI Approved :: MIT License
Classifier: Operating System :: OS Independent
Requires-Python: >=3.9
